README.md
setup.cfg
setup.py
fangcloud/__init__.py
fangcloud/base_type.py
fangcloud/collaboration_requests.py
fangcloud/comment_requests.py
fangcloud/exceptions.py
fangcloud/file_requests.py
fangcloud/folder_requests.py
fangcloud/helper.py
fangcloud/item_requests.py
fangcloud/oauth.py
fangcloud/session.py
fangcloud/share_link_requests.py
fangcloud/system_info.py
fangcloud/transport.py
fangcloud/trash_requests.py
fangcloud/trusted-certs.crt
fangcloud/url_builder.py
fangcloud/user_requests.py
fangcloud/yifangyun.py
fangcloud.egg-info/PKG-INFO
fangcloud.egg-info/SOURCES.txt
fangcloud.egg-info/dependency_links.txt
fangcloud.egg-info/not-zip-safe
fangcloud.egg-info/requires.txt
fangcloud.egg-info/top_level.txt