Metadata-Version: 1.2
Name: fangcloud
Version: 2.2.7
Summary: Official YiFangYun SDK for Open Platform
Home-page: https://www.yifangyun.com
Author: YiFangYun
Author-email: linrenjun@yifangyun.com
Maintainer: xiangyangyang
Maintainer-email: xiangyangyang@yifangyun.com
License: Apache Software License, Version 2.0, http://www.apache.org/licenses/LICENSE-2.0
Keywords: yifangyun api sdk
Platform: all
Classifier: Development Status :: 4 - Beta
Classifier: Intended Audience :: Developers
Classifier: Operating System :: POSIX
Classifier: Operating System :: Microsoft :: Windows
Classifier: Operating System :: MacOS :: MacOS X
Classifier: Programming Language :: Python :: 2.6
Classifier: Programming Language :: Python :: 2.7
Classifier: Programming Language :: Python :: 3.4
Classifier: Programming Language :: Python :: 3.5
Classifier: Topic :: Software Development :: Libraries :: Python Modules
